taipy/__init__.py
taipy/_cli/__init__.py
taipy/_cli/_base_cli/__init__.py
taipy/_cli/_base_cli/_cli.py
taipy/config/__init__.py
taipy/config/_config.py
taipy/config/_init.py
taipy/config/config.py
taipy/config/config.pyi
taipy/config/section.py
taipy/config/unique_section.py
taipy/config/version.json
taipy/config/version.py
taipy/config/_config_comparator/__init__.py
taipy/config/_config_comparator/_comparator_result.py
taipy/config/_config_comparator/_config_comparator.py
taipy/config/_serializer/__init__.py
taipy/config/_serializer/_base_serializer.py
taipy/config/_serializer/_json_serializer.py
taipy/config/_serializer/_toml_serializer.py
taipy/config/checker/__init__.py
taipy/config/checker/_checker.py
taipy/config/checker/issue.py
taipy/config/checker/issue_collector.py
taipy/config/checker/_checkers/__init__.py
taipy/config/checker/_checkers/_auth_config_checker.py
taipy/config/checker/_checkers/_config_checker.py
taipy/config/checker/_checkers/_global_config_checker.py
taipy/config/common/__init__.py
taipy/config/common/_classproperty.py
taipy/config/common/_config_blocker.py
taipy/config/common/_repr_enum.py
taipy/config/common/_template_handler.py
taipy/config/common/_validate_id.py
taipy/config/common/frequency.py
taipy/config/common/scope.py
taipy/config/exceptions/__init__.py
taipy/config/exceptions/exceptions.py
taipy/config/global_app/__init__.py
taipy/config/global_app/global_app_config.py
taipy/logger/__init__.py
taipy/logger/_taipy_logger.py
taipy_config-2.4.1.dist-info/LICENSE
taipy_config-2.4.1.dist-info/METADATA
taipy_config-2.4.1.dist-info/WHEEL
taipy_config-2.4.1.dist-info/top_level.txt
taipy_config-2.4.1.dist-info/RECORD
