Metadata-Version: 2.1
Name: taipy-config
Version: 2.4.1
Summary: A Taipy package dedicated to easily configure a Taipy application.
Home-page: https://github.com/avaiga/taipy-config
Author: Avaiga
Author-email: dev@taipy.io
License: Apache License 2.0
Keywords: taipy-config
Classifier: Intended Audience :: Developers
Classifier: License :: OSI Approved :: Apache Software License
Classifier: Natural Language :: English
Classifier: Programming Language :: Python :: 3
Classifier: Programming Language :: Python :: 3.8
Classifier: Programming Language :: Python :: 3.9
Classifier: Programming Language :: Python :: 3.10
Classifier: Programming Language :: Python :: 3.11
Requires-Python: >=3.8
License-File: LICENSE
Requires-Dist: toml <0.11,>=0.10
Requires-Dist: deepdiff <7.0,>=6.7
Requires-Dist: numpy <2.0
